{
  "510": "Everett – Seattle",
  "512": "Everett – Lynnwood",
  "513": "Seaway – Lynnwood",
  "515": "Lynnwood – Seattle",
  "522": "Woodinville – Roosevelt",
  "532": "Everett – Bellevue",
  "535": "Lynnwood – Bellevue",
  "542": "Redmond – University District",
  "545": "Redmond – Seattle",
  "550": "Bellevue – Seattle",
  "554": "Issaquah – Seattle",
  "556": "Issaquah – University District",
  "560": "Bellevue – West Seattle",
  "566": "Auburn – Redmond",
  "574": "Lakewood – Sea-Tac Airport",
  "577": "Federal Way – Seattle",
  "578": "Puyallup – Seattle",
  "580": "South Hill – Puyallup",
  "586": "Tacoma – University District",
  "590": "Tacoma – Seattle",
  "592": "DuPont – Seattle",
  "594": "Lakewood – Seattle",
  "595": "Gig Harbor – Seattle",
  "596": "Sumner – Bonney Lake"
}